Metadata-Version: 2.4
Name: mcp-data-analyzer-test
Version: 0.1.0
Summary: a mcp-data-analyzer mcp server
Requires-Python: >=3.13
Requires-Dist: mcp[cli]>=1.13.1
Requires-Dist: openpyxl>=3.1.5
Requires-Dist: pandas>=2.3.2
Requires-Dist: seaborn>=0.13.2
Requires-Dist: twine>=6.2.0
